{
    "coins": [
        {
            "id": 1,
            "x": 100,
            "y": 100,
            "radius": 100,
            "width": 20,
            "height": 20
        },
        {
            "id": 2,
            "x": 200,
            "y": 200,
            "radius": 100,
            "width": 20,
            "height": 20
        },
        {
            "id": 3,
            "x": 300,
            "y": 300,
            "radius": 100,
            "width": 20,
            "height": 20
        }
    ]
}